dtxg/__init__.py
dtxg/_common.py
dtxg/_version.py
dtxg/easter.py
dtxg/relativedelta.py
dtxg/rrule.py
dtxg/tzwin.py
dtxg/utils.py
dtxg/parser/__init__.py
dtxg/parser/_parser.py
dtxg/parser/country_tz.py
dtxg/parser/isoparser.py
dtxg/parser/locales.py
dtxg/tz/__init__.py
dtxg/tz/_common.py
dtxg/tz/_factories.py
dtxg/tz/tz.py
dtxg/tz/win.py
dtxg/zoneinfo/__init__.py
dtxg/zoneinfo/rebuild.py
dtxg-2.0.1.dist-info/METADATA
dtxg-2.0.1.dist-info/WHEEL
dtxg-2.0.1.dist-info/top_level.txt
dtxg-2.0.1.dist-info/RECORD
