Metadata-Version: 2.1
Name: dtxg
Version: 2.0.1
Summary: Extensions to the dateutil module to support time resolution in multiple languages
Home-page: https://github.com/yangsongbai1
Author: yangsongbai
Author-email: yang18734371940@gmail.com
Maintainer: yangsongbai
Maintainer-email: yang18734371940@gmail.com
License: BSD License
Platform: all
Classifier: Development Status :: 4 - Beta
Classifier: Operating System :: OS Independent
Classifier: Intended Audience :: Developers
Classifier: License :: OSI Approved :: BSD License
Classifier: Programming Language :: Python
Classifier: Programming Language :: Python :: Implementation
Classifier: Programming Language :: Python :: 2
Classifier: Programming Language :: Python :: 2.7
Classifier: Programming Language :: Python :: 3
Classifier: Programming Language :: Python :: 3.4
Classifier: Programming Language :: Python :: 3.5
Classifier: Programming Language :: Python :: 3.6
Classifier: Topic :: Software Development :: Libraries
Requires-Dist: pytz (>=2019.1)
Requires-Dist: six (>=1.5)
